MANIFEST.in
README.rst
ez_setup.py
setup.cfg
setup.py
versioneer.py
cerebro/__init__.py
cerebro/_cerebro_thrift_sasl.py
cerebro/_pure_sasl.py
cerebro/_pure_sasl_client.py
cerebro/_pure_sasl_mechanisms.py
cerebro/_thrift_api.py
cerebro/_util.py
cerebro/_version.py
cerebro/cdas.py
cerebro/thrift/CerebroRecordService.thrift
cerebro/thrift/RecordService.thrift
pycerebro.egg-info/PKG-INFO
pycerebro.egg-info/SOURCES.txt
pycerebro.egg-info/dependency_links.txt
pycerebro.egg-info/not-zip-safe
pycerebro.egg-info/requires.txt
pycerebro.egg-info/top_level.txt