Metadata-Version: 1.1
Name: pycerebro
Version: 0.8.2.1
Summary: Python client for the Cerebro Data Access Service
Home-page: UNKNOWN
Author: Cerebro Development Team
Author-email: UNKNOWN
License: Apache License, Version 2.0
Platform: UNKNOWN
Classifier: Development Status :: 4 - Beta
Classifier: Environment :: Console
Classifier: Operating System :: OS Independent
Classifier: Programming Language :: Python :: 3
Classifier: Programming Language :: Python :: 3.4
Classifier: Programming Language :: Python :: 3.5
